{
  "updated": "02.07.2026 10:30",
  "cbr_rate": 14.25,
  "total_inv": 4984865,
  "total_cur": 5150527,
  "total_pnl": 165662,
  "total_pnl_pct": 3.32,
  "bonds": [
    {
      "isin": "RU000A0JV4Q1",
      "name": "ОФЗ 29010",
      "qty": 200,
      "avg_price": 103.735,
      "price": 104.008,
      "ytm": 21.9,
      "pnl_rub": 546,
      "pnl_pct": 0.27,
      "ofz": true,
      "face_factor": 1.0,
      "nkd": null,
      "week_delta": "📉 за 8дн: -0.61%"
    },
    {
      "isin": "RU000A0JXFM1",
      "name": "ОФЗ 26221",
      "qty": 350,
      "avg_price": 61.368,
      "price": 69.437,
      "ytm": 15.65,
      "pnl_rub": 28242,
      "pnl_pct": 8.07,
      "ofz": true,
      "face_factor": 1.0,
      "nkd": null,
      "week_delta": "📉 за 8дн: -2.17%"
    },
    {
      "isin": "RU000A0ZYR91",
      "name": "ГТЛК БО 001Р-08",
      "qty": 250,
      "avg_price": 75.0,
      "price": 94.24,
      "ytm": 18.46,
      "pnl_rub": 48100,
      "pnl_pct": 19.24,
      "ofz": false,
      "face_factor": 1.0,
      "nkd": null,
      "week_delta": "📉 за 8дн: -0.03%"
    },
    {
      "isin": "RU000A100EF5",
      "name": "ОФЗ 26230",
      "qty": 535,
      "avg_price": 56.966,
      "price": 57.441,
      "ytm": 16.03,
      "pnl_rub": 2541,
      "pnl_pct": 0.48,
      "ofz": true,
      "face_factor": 1.0,
      "nkd": null,
      "week_delta": "📉 за 8дн: -2.22%"
    },
    {
      "isin": "RU000A1017J5",
      "name": "Газпром нефть БО-003P-02R",
      "qty": 300,
      "avg_price": 77.91,
      "price": 80.1,
      "ytm": 15.45,
      "pnl_rub": 6570,
      "pnl_pct": 2.19,
      "ofz": false,
      "face_factor": 1.0,
      "nkd": null,
      "week_delta": "📉 за 8дн: -0.96%"
    },
    {
      "isin": "RU000A1038V6",
      "name": "ОФЗ 26238",
      "qty": 600,
      "avg_price": 51.765,
      "price": 52.0,
      "ytm": 16.0,
      "pnl_rub": 1410,
      "pnl_pct": 0.23,
      "ofz": true,
      "face_factor": 1.0,
      "nkd": null,
      "week_delta": "📉 за 8дн: -2.30%"
    },
    {
      "isin": "RU000A102BV4",
      "name": "ОФЗ 29020",
      "qty": 400,
      "avg_price": 99.125,
      "price": 100.08,
      "ytm": 12.36,
      "pnl_rub": 3820,
      "pnl_pct": 0.95,
      "ofz": true,
      "face_factor": 1.0,
      "nkd": null,
      "week_delta": "📈 за 8дн: +0.08%"
    },
    {
      "isin": "RU000A10EMS7",
      "name": "СелоЗеленое 001Р-03",
      "qty": 250,
      "avg_price": 100.0,
      "price": 99.79,
      "ytm": 17.62,
      "pnl_rub": -525,
      "pnl_pct": -0.21,
      "ofz": false,
      "face_factor": 1.0,
      "nkd": null,
      "week_delta": "📈 за 8дн: +1.68%"
    },
    {
      "isin": "RU000A1033Z8",
      "name": "Гор.Обл.Займ Москвы 74",
      "qty": 370,
      "avg_price": 78.09,
      "price": 88.91,
      "ytm": 14.83,
      "pnl_rub": 40034,
      "pnl_pct": 10.82,
      "ofz": false,
      "face_factor": 1.0,
      "nkd": null,
      "week_delta": "📈 за 8дн: +0.23%"
    },
    {
      "isin": "RU000A10ASC6",
      "name": "ПАО ЛК Европлан 001P-09",
      "qty": 400,
      "avg_price": 101.32,
      "price": 108.97,
      "ytm": 15.47,
      "pnl_rub": 27540,
      "pnl_pct": 7.65,
      "ofz": false,
      "face_factor": 0.9,
      "nkd": null,
      "week_delta": "📈 за 8дн: +0.42%"
    },
    {
      "isin": "RU000A10DYC8",
      "name": "ФПК 002Р-01",
      "qty": 400,
      "avg_price": 100.47,
      "price": 101.61,
      "ytm": 15.44,
      "pnl_rub": 4560,
      "pnl_pct": 1.14,
      "ofz": false,
      "face_factor": 1.0,
      "nkd": null,
      "week_delta": "📉 за 8дн: -1.09%"
    },
    {
      "isin": "RU000A1025A7",
      "name": "ОФЗ 29015",
      "qty": 290,
      "avg_price": 98.823,
      "price": 99.45,
      "ytm": 12.48,
      "pnl_rub": 1818,
      "pnl_pct": 0.63,
      "ofz": true,
      "face_factor": 1.0,
      "nkd": null,
      "week_delta": "📈 за 8дн: +0.01%"
    },
    {
      "isin": "RU000A10EXZ9",
      "name": "МКПАО \"Озон\" 001Р-02",
      "qty": 200,
      "avg_price": 100.0,
      "price": 101.17,
      "ytm": 16.01,
      "pnl_rub": 2340,
      "pnl_pct": 1.17,
      "ofz": false,
      "face_factor": 1.0,
      "nkd": null,
      "week_delta": "📈 за 8дн: +0.22%"
    },
    {
      "isin": "RU000A10EA16",
      "name": "Почта России 003P-03",
      "qty": 360,
      "avg_price": 100.05,
      "price": 101.68,
      "ytm": 18.33,
      "pnl_rub": 5868,
      "pnl_pct": 1.63,
      "ofz": false,
      "face_factor": 1.0,
      "nkd": null,
      "week_delta": "📉 за 8дн: -0.72%"
    },
    {
      "isin": "RU000A105FZ9",
      "name": "ОФЗ 26241",
      "qty": 80,
      "avg_price": 81.463,
      "price": 78.081,
      "ytm": 15.5,
      "pnl_rub": -2706,
      "pnl_pct": -3.38,
      "ofz": true,
      "face_factor": 1.0,
      "nkd": null,
      "week_delta": "📉 за 8дн: -1.82%"
    },
    {
      "isin": "RU000A10EYW4",
      "name": "ПГК 003Р-05",
      "qty": 200,
      "avg_price": 100.0,
      "price": 100.3,
      "ytm": 17.11,
      "pnl_rub": 600,
      "pnl_pct": 0.3,
      "ofz": false,
      "face_factor": 1.0,
      "nkd": null,
      "week_delta": "📉 за 8дн: -0.59%"
    },
    {
      "isin": "RU000A10EYV6",
      "name": "ПГК 003Р-04",
      "qty": 300,
      "avg_price": 100.0,
      "price": 99.47,
      "ytm": 16.78,
      "pnl_rub": -1590,
      "pnl_pct": -0.53,
      "ofz": false,
      "face_factor": 1.0,
      "nkd": null,
      "week_delta": "📉 за 8дн: -0.52%"
    },
    {
      "isin": "RU000A10D4Y2",
      "name": "ОФЗ 26252",
      "qty": 120,
      "avg_price": 93.347,
      "price": 88.25,
      "ytm": 15.79,
      "pnl_rub": -6116,
      "pnl_pct": -5.1,
      "ofz": true,
      "face_factor": 1.0,
      "nkd": null,
      "week_delta": "📉 за 8дн: -2.25%"
    },
    {
      "isin": "RU000A10F470",
      "name": "ТрансКонтейнер П02-03",
      "qty": 300,
      "avg_price": 100.0,
      "price": 100.87,
      "ytm": 17.36,
      "pnl_rub": 2610,
      "pnl_pct": 0.87,
      "ofz": false,
      "face_factor": 1.0,
      "nkd": null,
      "week_delta": "📉 за 8дн: -0.55%"
    }
  ],
  "ai_corp": "# ПОРТФЕЛЬНЫЙ АНАЛИЗ И РЕКОМЕНДАЦИИ\n\n---\n\n## ЗАДАЧА 1: АНАЛИЗ КОРПОРАТИВНЫХ ОБЛИГАЦИЙ\n\n| Бумага | Рекомендация |\n|--------|--------------|\n| **ГТЛК БО 001Р-08** | РИСК=Средний \\| YTM 18.46% значительно выше КС, но дюрация 6.6л и сильный P&L (+48.1к₽) оправдывают позицию при возможном снижении ставок. \\| **ДЕРЖАТЬ** |\n| **Газпром нефть БО-003P-02R** | РИСК=Средний \\| Цена 80.1% с YTM 15.45% (спред 171 бп к КС) даёт хорошую маржу безопасности, но падение на 0.96% за 8 дн требует мониторинга. \\| **ДЕРЖАТЬ** |\n| **СелоЗеленое 001Р-03** | РИСК=Высокий \\| Убыток 525₽ при YTM 17.62% (спред 137 бп), позиция в минусе и нет компенсирующего спреда. \\| **СОКРАТИТЬ** |\n| **Гор.Обл.Займ Москвы 74** | РИСК=Низкий \\| Муниципальная облигация Москвы с низким спредом (58 бп к КС), коротким сроком (1.9л) и сильным P&L — госарантированная надёжность. \\| **ДЕРЖАТЬ** |\n| **ПАО ЛК Европлан 001P-09** | РИСК=Средний \\| Цена 108.97% выше безопасного уровня (108%), амортизация выполняется (face_factor 0.9), спред низкий (122 бп) — позиция переоценена. \\| **СОКРАТИТЬ** |\n| **ФПК 002Р-01** | РИСК=Низкий \\| ФПК — госкомпания, YTM 15.44% с низким спредом (119 бп), короткая дюрация (1.9л), падение на 1.09% временное. \\| **ДЕРЖАТЬ** |\n| **МКПАО \"Озон\" 001Р-02** | РИСК=Средний \\| Озон — качественный эмитент, YTM 16.01%, спред 76 бп к КС, но цена растёт (+0.22%) — позиция относительно справедлива. \\| **ДЕРЖАТЬ** |\n| **Почта России 003P-03** | РИСК=Средний \\| Дюрация 9.6 лет (максимальная в портфеле), YTM 18.33% высокая, но за 8 дн −0.72% падение при снижении ставок может быть значительнее. \\| **СОКРАТИТЬ** на 50% (переоценена по дюрации) |\n| **ПГК 003Р-05** | РИСК=Средний \\| Минимальный P&L (+600₽), YTM 17.11% (спред 86 бп), РЖД-подконтрольная; позиция нейтральна, но без явной выгоды. \\| **ДЕРЖАТЬ** |\n| **ПГК 003Р-04** | РИСК=Средний \\| Убыток 1.59к₽, YTM 16.78% (спред 53 бп), но это вторая ПГК в портфеле — две позиции одного эмитента в слабой динамике. \\| **СОКРАТИТЬ** (вместе с ПГК 003Р-05 выбрать более длинную) |\n| **ТрансКонтейнер П02-03** | РИСК=Средний \\| YTM 17.36% (спред 111 бп), минимальный P&L (+2.61к₽), дюрация 2.8л — нейтральная позиция без явных аргументов. \\| **ДЕРЖАТЬ** |\n\n---\n\n##",
  "ai_portfolio": "ЗАДАЧА 2: ПОРТФЕЛЬНЫЙ АНАЛИЗ\n\n### 📊 СТРУКТУРА ПОРТФЕЛЯ\n\n**Текущая стоимость:** 5,150,527₽  \n**P&L:** +165,662₽ (+3.3%)\n\n**Разбор по типам:**\n\n| Тип | Кол-во позиций | Примерный вес | Статус |\n|-----|---------|------|--------|\n| **ОФЗ** | 6 | ~45% | ДЕРЖАТЬ все (госбумаги) |\n| **Корпоративные (инвестиционный класс)** | 11 | ~55% | ТРЕБУЕТ ОПТИМИЗАЦИИ |\n\n---\n\n### ⚠️ ОБЩАЯ ОЦЕНКА\n\n**Портфель находится в хорошей прибыльности (+3.3%), но имеет избыточную концентрацию на корпоративах с высокой йеной (15.5–18.5%) при цикле снижения ставок.** Структура смещена в сторону коротких дюраций (1.9–3.4 года для большинства корпоративов), что защитит от роста ставок, но оставляет деньги на столе при их падении.\n\n**Критическое уязвимое место — две позиции Европлана (одна с амортизацией) и две ПГК ведут себя нестабильно, требуя переструктуризации.**\n\n---\n\n### 🎯 ГЛАВНЫЕ РИСКИ\n\n1. **Переоценка коротких корпоративов (1.9–2.3л) при цикле снижения ставок**  \n   Позиции типа ФПК, Москва-74, Озон и Европлан уже переоценены ценой выше 101% (Европлан 108.97%), но йеля низкая (58–122 бп к КС). Когда ставки упадут на 100–150 бп, эти облигации дадут только +1–2% прироста, а более длинные (6–9 лет) дадут +5–8%.\n\n2. **Концентрация на одном эмитенте и потеря диверсификации**  \n   ПГК занимает две позиции (003Р-05 и 003Р-04) с убыточной динамикой (−0.52 и −0.59% за 8 дн), Почта России с экстремальной дюрацией (9.6л) — риск переконцентрации на транспорте.\n\n---\n\n### 💡 ВОЗМОЖНОСТИ\n\n1. **Смена фокуса на длинные ОФЗ и корпоративы (5–10 лет) при цикле снижения ставок**  \n   Сейчас КС 14.25% и цикл снижения продолжается. Позиции типа ГТЛК (дюрация 6.6л, YTM 18.46%) и Почта России (9.6л, 18.33%) дадут максимум на落下 ставок, но требуют переделения портфеля.\n\n2. **Купить длинные ОФЗ (ОФЗ 29010–29020 с дюрациями 5+) на падении ставок**  \n   ОФЗ 29010 (YTM 21.9%) уже в портфеле — пусть будут якорь при падении. Добавить ОФЗ с дюрацией 7–10 лет с текущей йеной 16–17%.\n\n---\n\n### 🚀 ТОП-3 ДЕЙСТВИЯ (КОНКРЕТНО)\n\n#### **ДЕЙСТВИЕ 1: СОКРАТИТЬ ПЕРЕОЦЕНЕННЫЕ КОРОТКИЕ КОРПОРАТИВЫ**\n\n- **Европлан 001P-09: продать 200 шт из 400 (55.0к₽)**  \n  Цена 108.97% выше безопасного 108%, спред только 122 бп, амортизация (face_factor 0.9) означает купоны считаются на 900₽ — это скрытое снижение йели. При падении ставок на 150 бп облигация не даст никакого прироста.\n\n- **ПАО ЛК Европлан + ПГК: переделить портфель**  \n  Есть две позиции ПГК с убыточной динамикой. Оставить только ПГК 003Р-05 (дюрация 2.3л, спред 86 бп), ПГК 003Р-04 сократить полностью (−1.59к₽).  \n  **Сумма к реинвестированию: ~60–70к₽**\n\n#### **ДЕЙСТВИЕ 2: КУПИТЬ ДЛИННЫЕ ПОЗИЦИИ ДЛЯ ЦИКЛА СНИЖЕНИЯ СТАВОК**\n\n- **Добавить ОФЗ с дюрацией 7–10 лет (цель: +20–25% в портфель)**  \n  Пример: ОФЗ 26238 (уже есть, надо докупить) или ОФЗ 29010 (YTM 21.9%, дюрация макс).  \n  **При падении ставок на 150 бп длинная ОФЗ даст +12–15% прироста.**\n\n- **Держать ГТЛК 001Р-08 (дюрация 6.6л, YTM 18.46%) — это якорь на циклe.**  \n  P&L +48.1к₽ оправдывает позицию. НЕ сокращать.\n\n#### **ДЕЙСТВИЕ 3: СОКРАТИТЬ УБЫТОЧНЫЕ И ВЫСОКОДЮРАЦИОННЫЕ ПОЗИЦИИ**\n\n- **Почта России 003P-03: продать 180 шт из 360 (установить дюрацию ~5л макс)**  \n  Дюрация 9.6л — это экстремум для портфеля ~5м₽. При кратковременном падении ставок получим прибыль, но если ставки вернутся вверх, потеря будет резкой. Оставить 180 шт (54к₽), получить ~3к₽ дополнительно при падении ставок на 100 бп.\n\n- **СелоЗеленое 001Р-03: полностью выйти (убыток −525₽, YTM 17.62% при спреде только 137 бп)**  \n  Дюрация 4.7л, нет компенсирующей маржи. Реинвестировать в ОФЗ или ГТЛК.\n\n---\n\n## 📋 ИТОГОВАЯ ТАБЛИЦА РЕКОМЕНДАЦИЙ\n\n| Бумага | Текущ. позиция | Действие | Причина |\n|--------|------|---------|---------|\n| **ГТЛК БО 001Р-08** | 250 шт (+48.1к₽) | ✅ ДЕРЖАТЬ | Якорь на цикл снижения (6.6л, +18.46%) |\n| **Газпром нефть БО-003P-02R** | 300 шт (+6.6к₽) | ✅ ДЕРЖАТЬ | Инвестград, спред 171 бп, дюрация 3.4л OK |\n| **СелоЗеленое 001Р-03** | 250 шт (−525₽) | 🔴 **ПРОДАТЬ ВСЕ** | Убыток, спред 137 бп, дюрация 4.7л не оправдана |\n| **Гор.Обл.Займ Москвы 74** | 370 шт (+40.0к₽) | ✅ ДЕРЖАТЬ | Москва-гарантия, спред 58 бп, короткая (1.9л) |\n| **Европлан 001P-09** | 400 шт (+27.5к₽) | 🟡 **СОКРАТИТЬ на 50%** | Цена 108.97% > 108%, спред 122 бп, амортизация |\n| **ФПК 002Р-01** | 400 шт (+4.6к₽) | ✅ ДЕРЖАТЬ | Госкомпания, спред 119 бп, дюрация 1.9л OK |\n| **Озон 001Р-02** | 200 шт (+2.3к₽) | ✅ ДЕРЖАТЬ | Качественный эмитент, спред 76 бп |\n| **Почта России 003P-03** |"
}